{
  "parameters": {
    "route_name": "Route 11_07 23_2021",
    "route_date": 1627257600,
    "route_time": 21600,
    "optimize": "Distance",
    "travel_mode": "Driving",
    "rt": false,
    "locked_last": true,
    "algorithm_type": 9,
    "bundling": null,
    "advanced_constraints": [
      {
        "max_cargo_volume": 0,
        "max_capacity": 3,
        "members_count": 10,
        "available_time_windows": [
          [
            25200,
            75000
          ]
        ],
        "location_sequence_pattern": [
          "",
          {
            "alias": "DEPOT END LOCATION",
            "address": "8100 Boone Blvd,Vienna,VA 22182.USA",
            "lat": 38.9137506,
            "lng": -77.2258757,
            "time": 300
          }
        ]
      },
      {
        "max_cargo_volume": 0,
        "max_capacity": 3,
        "members_count": 10,
        "available_time_windows": [
          [
            45200,
            95000
          ]
        ],
        "location_sequence_pattern": [
          "",
          {
            "alias": "DEPOT END LOCATION",
            "address": "8100 Boone Blvd,Vienna,VA 22182.USA",
            "lat": 38.9137506,
            "lng": -77.2258757,
            "time": 300
          }
        ]
      }
    ]
  },
  "addresses": [
    {
      "address": "1029 Green Acre Dr, Strasburg, VA 22657, USA",
      "address_stop_type": null,
      "is_depot": true,
      "lat": 39.0021212,
      "lng": -78.3832986,
      "visited_lat": null,
      "visited_lng": null,
      "departed_lat": null,
      "departed_lng": null,
      "curbside_lat": null,
      "curbside_Ing": null,
      "bundle_count": 0,
      "bundle_items": null,
      "order inventory": null,
      "tags": null
    },
    {
      "address": "11900 LIVINGSTON RD STE 161, MANASSAS, VA 20110",
      "address_stop_type": null,
      "lat": 38.7848718,
      "lng": -77.5497293,
      "route_name": "Route 1107 23_2021",
      "visited_lat": null,
      "visited_lng": null,
      "departed_lat": null,
      "departed_lng": null,
      "order_no": "2963650",
      "weight": 78.0,
      "time": 600,
      "curbside_lat": null,
      "curbside_lng": null,
      "bundle_count": 0,
      "bundle_items": null,
      "order_inventory": null,
      "tags": [ "Order" ]
    },
    {
      "address": "4300 Chantilly Shopping Ctr, SUITE 2G, CHANTILLY, VA 20151, USA",
      "address_stop type": null,
      "lat": 38.8864393,
      "lng": -77.4412848,
      "route_name": "Route 1107_23_2021",
      "visited_lat": null,
      "visited_lng": null,
      "departed_lat": null,
      "departed_lng": null,
      "order no": "2963319",
      "weight": 51.0,
      "time": 600,
      "curbside_lat": null,
      "curbside_lng": null,
      "bundle_count": 0,
      "bundle_items": null,
      "order inventory": null,
      "tags": [ "Order" ]
    },
    {
      "address": "44156 MERCURE CIR, STERLING, VA 20166, USA",
      "address_stop_type": null,
      "lat": 38.9858689,
      "lng": -77.4808627,
      "route_name": "Route 1107_23_2021",
      "visited_lat": null,
      "visited_lng": null,
      "departed_lat": null,
      "departed_lng": null,
      "order_no": "29637417",
      "weight": 50.0,
      "time": 600,
      "curbside_lat": null,
      "curbside_lng": null,
      "bundle_count": 0,
      "bundle_items": null,
      "order_inventory": null,
      "tags": [ "Order" ]
    },
    {
      "address": "801 CEDAR CREEK GRADE, WINCHESTER, VA 22601, USA",
      "address_stop_type": null,
      "lat": 39.162887,
      "lng": -78.1905699,
      "route_name": "Route 11_07 23_2021",
      "visited_lat": null,
      "visited_lng": null,
      "departed_lat": null,
      "departed_lng": null,
      "order_no": "2963144",
      "weight": 51.0,
      "time": 600,
      "curbside_lat": null,
      "curbside_lng": null,
      "bundle_count": 0,
      "bundle_items": null,
      "order_inventory": null,
      "tags": [ "Order" ]
    },
    {
      "address": "IMAGE360 - DULLES, 45449 SEVERN WAY - SUITE 173, DULLES, VA 20166, USA",
      "address_stop_type": null,
      "lat": 39.0202502,
      "lng": -77.4270975,
      "route_name": "Route 1107_23_2021",
      "visited_lat": null,
      "visited_lng": null,
      "departed_lat": null,
      "departed_lng": null,
      "order_no": "2963823,2963839,2963916",
      "weigh": 80.0,
      "time": 600,
      "curbside_lat": null,
      "curbside_lng": null,
      "bundle_count": 0,
      "bundle_items": null,
      "order_inventory": null,
      "tags": [ "Order" ]
    }
  ]
}
